<?xml version="1.0" encoding="UTF-8"?><i><chatserver>chat.bilibili.com</chatserver><chatid>3262388</chatid><mission>0</mission><maxlimit>500</maxlimit><max_count>500</max_count><d p="41.114,1,25,16777215,1425714633,0,4cbdf6bf,837981845">blibliblibliblibliblibli</d>
<d p="57.035,1,25,16777215,1425727105,0,efdc7fca,837981850">BLIBLIBLIBLBI</d>
<d p="6.8,5,25,41194,1425729753,0,e87fd44d,837981851">酱酱酱！！！</d>
<d p="46.531,1,25,16777215,1425732478,0,bb9ad5b9,837981853">发现镇站之宝</d>
<d p="61.284,1,25,16777215,1425732556,0,37a92cdc,837981854">哔哩哔哩</d>
<d p="79.256,1,25,16777215,1425732574,0,37a92cdc,837981855">哔哩哔哩哔哩哔哩哔哩哔哩</d>
<d p="22.471,1,25,16707842,1425734433,0,b9ae5fae,837981856">我来顶一个~</d>
<d p="35.608,1,25,16707842,1425734497,0,b9ae5fae,837981857">2015.3.7 21:23</d>
<d p="54.528,1,25,16737792,1425739718,0,0fc0f1ad,837981859">15.3.7 BILIBILIBILIBILIBILIBILIBILI</d>
<d p="40.856,1,25,16777215,1425745648,0,c2f23eca,837981861">弹幕好可怕</d>
<d p="80.554,1,25,16777215,1425775639,0,8525e1ad,837981863">如此凶残的弹幕</d>
<d p="34.698,1,25,16777215,1425778413,0,c76c348b,837981864">卡的不行</d>
<d p="72.568,1,25,16777215,1425778451,0,c76c348b,837981865">幼女好评</d>
<d p="23.927,1,25,16777215,1425780212,0,De74fbdb,837981866">哔哩哔哩</d>
<d p="75.97,1,25,16711680,1425782152,0,771b4481,837981868">2015.3.8</d>
<d p="23.556,1,25,16777215,1425783505,0,c6da44c8,837981869">(*/ω＼*)我竟然看过</d>
<d p="8.278,1,25,16777215,1425783683,0,221c9ad9,837981870">23333</d>
<d p="0,4,25,65280,1425784167,0,1220c3ff,837981872">蒽蒽</d>
<d p="53.761,1,25,16777215,1425784299,0,ec42c0dd,837981873">什么时候被顶上来的</d>
<d p="80.865,1,25,16711935,1425784327,0,ec42c0dd,837981874">哔哩哔哩</d>
<d p="30.84,1,25,16777215,1425784803,0,224a3ac2,837981876">又被顶上来了。。。。</d>
<d p="33.649,1,25,16777215,1425787274,0,607d183a,837981878">314</d>
<d p="93.303,1,25,16777215,1425788333,0,ea34367e,837981879">bilibili</d>
<d p="52.501,1,25,16777215,1425791005,0,c843a966,837981881">哔哩哔哩</d>
<d p="35.893,1,25,16777215,1425792274,0,6adec2cd,837981883">才500弹幕，说好的镇站之宝呢？</d>
<d p="26.91,1,25,13395558,1425792305,0,2261bc57,837981884">哔哩哔哩哔哩哔哩哔哩哔哩哔哩</d>
<d p="41.25,1,25,16777215,1425792308,0,Db0cc64f,837981885">哔哩哔哩哔哩哔哩哔哩哔哩</d>
<d p="29.855,4,25,10092288,1425792356,0,2261bc57,837981887">哔哩哔哩哔哩哔哩</d>
<d p="8.43,1,25,16777215,1425792872,0,98f65f81,837981888">镇站之宝</d>
<d p="21.66,1,25,16777215,1425793415,0,972cae2c,837981889">留个记号</d>
<d p="67.329,1,25,10053171,1425794233,0,ca233a64,837981891">200W！</d>
<d p="2.16,5,25,16777215,1425794289,0,722bdfe8,837981893">万恶之源</d>
<d p="6.672,1,25,16777215,1425795264,0,4d172777,837981894">wwwwwww</d>
<d p="0,1,25,16737843,1425795322,0,3252d847,837981895">恭喜破200W</d>
<d p="14.996,1,25,16777215,1425795955,0,4d172777,837981896">顶顶顶顶顶</d>
<d p="22.514,1,25,16777215,1425796180,0,1b4b9695,837981897">哔哩哔哩</d>
<d p="12.28,1,25,16777215,1425799521,0,ed55e099,837981899">bilibili</d>
<d p="46.144,1,25,3381759,1425805004,0,3b10a71d,837981901">哔哩哔哩哔哩哔哩哔哩哔哩</d>
<d p="0,1,25,16776960,1425805094,0,3e0a7508,837981902">怎么又上来了？？</d>
<d p="0.54,1,25,16776960,1425805343,0,3e0a7508,837981903">播放数2014251~</d>
<d p="95.488,1,25,16777215,1425805975,0,a6dce7f6,837981905">第一次来刷……</d>
<d p="8.044,1,25,16777215,1425806031,0,a6dce7f6,837981906">炮姐一生推！！！</d>
<d p="18.425,1,25,16777215,1425806043,0,a6dce7f6,837981907">太赞了</d>
<d p="30.716,1,25,16777215,1425806055,0,a6dce7f6,837981908">弹幕这么少不科学……</d>
<d p="38.796,1,25,16777215,1425806443,0,8512dee4,837981911">billbill</d>
<d p="29.151,1,25,16777215,1425806993,0,e7fd174d,837981913">自动循环</d>
<d p="33.61,1,25,16777215,1425807038,0,91bbfb27,837981914">哔哩哔哩哔哩哔哩</d>
<d p="45.222,1,25,3381555,1425807050,0,91bbfb27,837981915">哔哩哔哩哔哩哔哩</d>
<d p="24.234,5,25,65535,1425809917,0,3f3d4152,837981916">弹幕被清了</d>
<d p="1.762,1,25,16777215,1425812267,0,03ec110e,837981917">200万</d>
<d p="46.059,1,25,16777215,1425812655,0,D24ddac2,837981918">no</d>
<d p="0,1,25,16777215,1425812832,0,c76c348b,837981921">又顶上来了</d>
<d p="80.061,1,25,16777215,1425812867,0,D1f7ac56,837981922">中国话的你够了</d>
<d p="2.466,1,25,16777215,1425813616,0,D322e747,837981923">镇站之宝</d>
<d p="1.056,1,25,16777215,1425813745,0,D322e747,837981925">等等，自带循环？</d>
<d p="84.36,1,25,52428,1425814059,0,a6fc6ec8,837981926">哔哩哔哩哔哩哔哩哔哩哔哩</d>
<d p="72.034,1,25,16777215,1425818022,0,1eb0e1ef,837981927">GANDINGGANKAN</d>
<d p="85.397,1,25,16777215,1425818035,0,1eb0e1ef,837981928">敢顶敢看</d>
<d p="6.83,1,25,16777215,1425818955,0,fe614aa5,837981929">来B站就是为了看炮姐</d>
<d p="23.43,1,25,16777215,1425819130,0,09be63dc,837981930">hhhhhhh</d>
<d p="76.469,1,25,16777215,1425819161,0,fe614aa5,837981931">靠，炮姐都被弹幕挡住啦！！！！！！！！！</d>
<d p="27.629,1,25,16777215,1425819568,0,fe614aa5,837981933">一不小心听了50多遍，感觉大脑都麻木了啊</d>
<d p="42.019,1,25,16777215,1425821699,0,D800c6f7,837981934">bilibilibilibilibili</d>
<d p="84.595,1,25,16777215,1425822099,0,Dd963db5,837981935">wwww</d>
<d p="44.847,1,25,16777215,1425822303,0,b0f65184,837981936">bilibilibilibili</d>
<d p="68.175,1,25,3355494,1425822348,0,e0af446b,837981937">哔哩哔哩</d>
<d p="55.102,1,25,16777215,1425822365,0,b0f65184,837981938">酱酱酱</d>
<d p="36.227,1,25,16777215,1425822663,0,d642c1d3,837981940">哔哩哔哩哔哩哔哩哔哩哔哩</d>
<d p="6.232,1,25,16777215,1425822848,0,d642c1d3,837981941">炮姐这是太可爱了</d>
<d p="83.424,1,25,16777215,1425857308,0,0ef98e90,837981942">bilibili</d>
<d p="0,1,25,16777215,1425857388,0,2201ffd1,837981943">见炮滚</d>
<d p="9.947,1,25,16777215,1425857664,0,De056dbd,837981944">自动循环什么鬼！！</d>
<d p="94.687,1,25,16777215,1425871268,0,fe614aa5,837981945">真是射得满屏都是呀</d>
<d p="84.564,1,25,16777215,1425874876,0,Dc4861c5,837981946">2333333333333</d>
<d p="4.639,1,25,41194,1425878996,0,167aff35,837981947">万恶之源</d>
<d p="50.122,5,25,16711680,1425879436,0,4df9925d,837981948">2015.3.9号，有人比我更晚？？？？</d>
<d p="55.619,1,25,16711680,1425884756,0,bd4a80a7,837981950">200W贺电</d>
<d p="29.611,1,25,16777215,1425888837,0,36ff0479,837981951">害羞炮姐哟哟哟</d>
<d p="54.76,1,25,16777215,1425894437,0,Db166ada,837981952">bilibili</d>
<d p="22.981,1,25,16777215,1425894580,0,d100edaa,837981953">~</d>
<d p="14.62,1,25,16777215,1425894668,0,40badb05,837981954">炮姐太可爱了</d>
<d p="5.864,1,25,16777215,1425894814,0,b4a07e6b,837981955">卧槽</d>
<d p="10.16,1,25,16777215,1425894870,0,abb2dc19,837981956">200W</d>
<d p="33.603,1,25,16777215,1425894930,0,03849b87,837981957">哔哩哔哩哔哩哔哩</d>
<d p="66.065,1,25,16777215,1425894986,0,03849b87,837981958">哔哩哔哩哔哩哔哩</d>
<d p="75.059,1,25,16777215,1425894964,0,03849b87,837981959">哔哩哔哩哔哩哔哩</d>
<d p="16.629,1,25,16777215,1425895158,0,9f6fc0ec,837981960">又起来了</d>
<d p="23.045,1,25,16777215,1425895082,0,efdf7c25,837981961">隔几天来看就发现弹幕又被清。一次又一次</d>
<d p="61.8,5,25,16711680,1425895331,0,0e4765f1,837981962">镇站之宝又上来了</d>
<d p="94.349,4,25,16711680,1425896044,0,e82fa896,837981964">bilibili</d>
<d p="25.601,1,25,41194,1425898529,0,2bab8d81,837981965">233333333333333333</d>
<d p="91.31,1,25,15138834,1425898436,0,19e6e13d,837981966">15.3.9</d>
<d p="52.031,1,25,6830715,1425898508,0,d5c86681,837981967">2015.3.9   作业之前来一发</d>
<d p="56.036,1,25,16777215,1425902491,0,0c5d5f3c,837981969">2015.3.9等我！</d>
<d p="25.356,1,25,16777215,1425905014,0,Dd777019,837981971">.</d>
<d p="63.259,1,25,16777215,1425905052,0,Dd777019,837981972">.</d>
<d p="8.674,1,25,41194,1425906594,0,3a471699,837981973">前来回顾镇站之歌</d>
<d p="52.68,1,25,16777215,1425906661,0,D9dc8c11,837981974">2015.3.9的吾在这里！！！</d>
<d p="0.577,1,25,16777215,1425906836,0,7f621641,837981975">up又把镇站之宝挖出来了...........</d>
<d p="34.806,1,25,16737843,1425906878,0,663851d2,837981976">又上来了</d>
<d p="57.545,1,25,16737843,1425906900,0,663851d2,837981977">真·神弹幕</d>
<d p="84.484,5,25,16737843,1425906903,0,663851d2,837981978">这凶残的弹幕...</d>
<d p="12.687,1,25,16777215,1425907178,0,9cad7a5a,837981979">我老炮</d>
<d p="42.958,1,25,16777215,1425907221,0,9cad7a5a,837981980">这个弹幕什么情况</d>
<d p="79.405,1,25,16777215,1425910477,0,4455f2f1,837981982">哔哩哔哩哔哩哔哩哔哩哔哩</d>
<d p="20.93,1,25,16777215,1425910568,0,0cfecc9e,837981983">又被顶上来了</d>
<d p="37.486,1,25,16777215,1425911029,0,19dd8966,837981984">哔哩哔哩哔哩哔哩</d>
<d p="9.15,1,25,16777215,1425913467,0,eb04ee5a,837981985">=-=</d>
<d p="32.533,1,25,16777215,1425919047,0,80eb9b86,837981986">吃我一记洛阳铲</d>
<d p="2.321,4,25,16777215,1425921415,0,648049bc,837981987">2015.3.10凌晨2点</d>
<d p="51.388,1,25,16777215,1425925661,0,e22ae020,837981989">2015 3 15</d>
<d p="22.96,1,25,16777215,1425949495,0,46abca57,837981990">bilibili</d>
<d p="55.31,1,25,15138834,1425960211,0,ff75acd6,837981994">2015.3.10</d>
<d p="2.2,1,25,16777215,1425963050,0,1a305d43,837981995">电磁炮</d>
<d p="2.4,1,25,16777215,1425963391,0,1a305d43,837981996">电磁炮电磁炮电磁炮</d>
<d p="44.543,1,25,16777215,1425968474,0,cd81b0b0,837981997">哔哩哔哩哔哩</d>
<d p="63.818,1,25,16777215,1425972515,0,29a56800,837981998">哔哩哔哩</d>
<d p="75.209,4,25,65484,1425972495,0,29a56800,837981999">哔哩哔哩</d>
<d p="20.067,1,25,41194,1425980872,0,3d4c2927,837982000">成为会员了，来一发</d>
<d p="54.195,5,25,16777215,1425983980,0,e000c025,837982002">不好意思，3.10</d>
<d p="17.42,1,25,16777215,1425984266,0,866ade17,837982003">哔哩哔哩哔哩哔哩哔哩哔哩</d>
<d p="50.04,1,25,16777215,1425993445,0,cf7f7145,837982004">弹幕都清光了</d>
<d p="24.218,1,25,16777215,1425994632,0,D27404d5,837982006">征战之宝</d>
<d p="10.188,1,25,16777215,1425995149,0,3d08a969,837982007">又顶上来了？！</d>
<d p="24.686,1,25,16777215,1425995734,0,75809691,837982009">哔哩哔哩</d>
<d p="77.302,1,25,16711680,1425996817,0,ab90ed65,837982010">满眼的哔哩哔哩</d>
<d p="82.076,1,25,16777215,1425997753,0,a0501b90,837982011">2015.3.10</d>
<d p="38.547,1,25,16777215,1425997822,0,Ddfe5dd4,837982012">哔哩哔哩</d>
<d p="25.872,1,25,16777215,1425998074,0,0ffb2d28,837982013">20150310！我的妹妹御坂美琴世界第一可爱！！！</d>
<d p="83.081,1,25,16777215,1426047207,0,871ab2a4,837982014">见炮滚</d>
<d p="27.761,1,25,16777215,1426055979,0,e821e068,837982016">lallalalallalalalallaaaaaa </d>
<d p="61.306,1,25,16777215,1426056012,0,e821e068,837982017">3月11的在此</d>
<d p="67.071,1,25,16777215,1426064061,0,cb747238,837982018">2015.3.11</d>
<d p="8.138,4,25,16777215,1426065732,0,fdf3b4c7,837982019">谁又顶上来的，好屌啊</d>
<d p="36.211,1,25,16777215,1426072405,0,2401d034,837982020">独享留念</d>
<d p="5.645,1,25,16777215,1426073799,0,efdf7c25,837982022">镇站之宝</d>
<d p="80.15,1,25,13434879,1426074002,0,154c52a5,837982023">哔哔哔哔哔哔哔哔ibibibiibibibi</d>
<d p="80.082,4,25,15138834,1426074509,0,e82fa896,837982024">哔哩哔哩酱~~~</d>
<d p="11.292,1,25,16777215,1426074841,0,da9fe499,837982025">哔哩哔哩</d>
<d p="10.745,1,25,16777215,1426076841,0,a3f599d8,837982026">比例比例比例比</d>
<d p="59.799,5,25,15597585,1426077706,0,b8a68a16,837982027">三月十一</d>
<d p="8.01,1,25,16777215,1426077739,0,9f9e1ece,837982028">每日一遍、</d>
<d p="24.877,1,25,16777215,1426077756,0,9f9e1ece,837982029">哔哩哔哩、、</d>
<d p="21.92,1,25,16777215,1426077863,0,75911696,837982030">bilibili</d>
<d p="31.906,1,25,16777215,1426077873,0,75911696,837982031">哔哩哔哩白</d>
<d p="26.494,4,25,16711680,1426077919,0,12650866,837982032">是谁干的！！！！！！！！</d>
<d p="64.598,1,25,16707842,1426077934,0,41979fa1,837982033">同3.11</d>
<d p="24.398,1,25,16777215,1426081642,0,f337a15c,837982034">哔哩哔哩哔哩哔哩</d>
<d p="32.586,1,25,16777215,1426081756,0,bccd6f97,837982035">哔哩哔哩哔哩哔哩</d>
<d p="38.767,1,25,6737151,1426117146,0,0c16b64c,837982038">2015/3/12独享成功</d>
<d p="10.987,1,25,16777215,1426117724,0,9bc28c0f,837982039">2015.3.12</d>
<d p="4.046,1,25,16777215,1426126986,0,ae7974e5,837982041">炮姐</d>
<d p="84.152,1,18,16777215,1426135488,0,D062fa8d,837982042">弹幕被清了…不过好赞</d>
<d p="54.924,1,25,16777215,1426137377,0,87d4aff0,837982043">哔哩哔哩</d>
<d p="76.459,1,25,16777215,1426137562,0,D6b8c414,837982044">我的娘啊，这是啥=-=</d>
<d p="93.96,1,25,16777215,1426137580,0,D6b8c414,837982045">Index乱入</d>
<d p="58.365,1,25,16777215,1426139220,0,D3315592,837982046">2015.3.12</d>
<d p="8.061,1,25,16777215,1426145187,0,5f6581c8,837982047">bilibili~</d>
<d p="45.166,1,25,16777215,1426146609,0,dd0989ee,837982048">大爱</d>
<d p="69.415,1,25,16777215,1426146637,0,dd0989ee,837982049">3.12</d>
<d p="8.106,1,25,16777215,1426152217,0,cd707e32,837982051">哔哩哔哩哔哩哔哩</d>
<d p="73.881,1,25,16777215,1426152447,0,9a981337,837982053">2015.3.12</d>
<d p="48.104,1,25,16777215,1426154566,0,2d2671e8,837982054">bilibili</d>
<d p="2.51,1,25,16777215,1426155994,0,84c8be38,837982055">自带循环。。</d>
<d p="72.257,1,25,16777215,1426157719,0,Dbd58f7f,837982056">BILIBILIBILI</d>
<d p="18.09,1,25,16777215,1426158486,0,c76c348b,837982057">再来一遍</d>
<d p="54.946,1,25,16777215,1426158557,0,c76c348b,837982058">弹幕都被清掉了</d>
<d p="60.883,1,25,16777215,1426159275,0,De4b897a,837982059">。</d>
<d p="67.86,1,25,13369344,1426163277,0,e28afeaf,837982061">bilibilibili</d>
<d p="44.941,1,25,16777215,1426169499,0,a3ca2704,837982062">前面3/12的你好</d>
<d p="80.238,1,25,16777215,1426169600,0,2977ff7f,837982063">反正再也不用担心左舷弹幕不够了随便发点什么就行了</d>
<d p="7.64,5,25,9487136,1426171661,0,e87fd44d,837982064">3.10 bilibili。。</d>
<d p="55.88,5,25,9487136,1426171724,0,e87fd44d,837982065">3.10在此！</d>
<d p="72.704,1,25,16777215,1426172042,0,d29bbea2,837982066">2015.3.12 求虐</d>
<d p="86.645,1,25,16777215,1426172493,0,2da30061,837982067"> 哔哩哔哩</d>
<d p="60.462,1,25,16777215,1426172617,0,D17fce82,837982069">2015.3.10在此求同胞～</d>
<d p="3.112,1,25,16777215,1426172713,0,2d54495b,837982070">200w恭喜</d>
<d p="32.731,1,25,16777215,1426174695,0,daf97c48,837982071">哔哩哔哩哔哩哔哩哔哩哔哩</d>
<d p="44.941,1,25,16777215,1426174943,0,ec9ac62d,837982072">毕哩</d>
<d p="0,1,25,16777215,1426181593,0,45decf67,837982076">成为B站正式会员的第一个弹幕先给镇站之宝</d>
<d p="32.862,1,25,16777215,1426193837,0,e4c22308,837982077">哔哩哔哩</d>
<d p="38.794,1,25,16777215,1426193866,0,e4c22308,837982078">哔哩哔哩</d>
<d p="74.23,1,25,16777215,1426194096,0,c568611a,837982079">bilibili万岁！！！</d>
<d p="63.099,1,25,16777215,1426221449,0,7dbd7321,837982080">2015 2 13路过</d>
<d p="5.557,1,25,16777215,1426517941,0,cba7065a,837985749">bilibili</d>
<d p="6.809,1,25,16777215,1426517959,0,cba7065a,837986517">镇站之宝~~~</d>
<d p="78.1,1,25,16777215,1426520356,0,97909afc,838030775">3月16在此 2015 03 16</d>
<d p="83.809,1,25,16777062,1426521254,0,34faaee0,838044364">2015/3/16的站住</d>
<d p="38.988,1,25,16777215,1426521885,0,557a1de7,838053357">哔哩哔哩哔哩哔哩</d>
<d p="23.244,1,25,16777215,1426523705,0,5dcc276d,838075126">2015.3.17</d>
<d p="16.662,1,25,16777215,1426526756,0,ecd84c83,838100991">主页看见必进！</d>
<d p="9.01,1,25,16777215,1426527136,0,D2462990,838103529">2015 3 17   你服不</d>
<d p="14.052,1,25,16777215,1426527165,0,c85d8a70,838103852">我居然听了好几遍.......</d>
<d p="36.166,1,25,16777215,1426558509,0,e029a519,838207468">哔哩哔哩哔哩哔哩</d>
<d p="65.69,1,25,16777215,1426558538,0,e029a519,838207607">同为萝莉控前面的等我</d>
<d p="93.918,1,25,16777215,1426558527,0,e029a519,838207766">哔哩哔哩赛高</d>
<d p="71.298,1,25,10040166,1426558851,0,51a5c6bb,838209261">哔哩哔哩哔哩哔哩</d>
<d p="15.731,1,25,16777215,1426565013,0,017f3294,838255547">自带循环~~~~ 欢迎回来！</d>
<d p="46.053,1,25,16711680,1426565207,0,d59bc522,838257104">敢顶就敢看</d>
<d p="42.028,1,25,16777215,1426567170,0,Dc1c772b,838294779">0</d>
<d p="53.8,5,25,16707842,1426568610,0,9040767b,838315087">真希望看到十五万弹幕出现</d>
<d p="0,1,25,16777215,1426579375,0,c76c348b,838412669">镇站之宝</d>
<d p="20.239,1,25,16777215,1426586071,0,9be5f78f,838499344">哔哩哔哩</d>
<d p="61.217,1,25,16777215,1426586217,0,D0b12dad,838501247">御坂御坂赛高</d>
<d p="66.721,1,25,16777215,1426586235,0,D0b12dad,838501473">御坂妹妹  御坂御坂赛高</d>
<d p="16.582,1,25,16777215,1426586474,0,D952c80b,838504552">最近弹幕都好屌、、、、</d>
<d p="59.38,1,25,26367,1426586604,0,da7f7cb0,838506175">哔哩哔哩哔哩哔哩</d>
<d p="13.809,1,25,16777215,1426586590,0,71aaee3a,838506211">bilibili</d>
<d p="7,1,25,16777215,1426592642,0,e4000541,838611625">%E5%9B%9E%E6%9D%A5%E4%BA%86</d>
<d p="0.656,1,25,16777215,1426593131,0,88685ae5,838618557">镇站之宝复活啦</d>
<d p="17.959,1,25,16777215,1426595512,0,7ed3a007,838664891">哔哩哔哩</d>
<d p="55.046,1,25,16777215,1426597612,0,De2101bb,838708288">跪了跪了</d>
<d p="0.068,1,25,16777215,1426598402,0,a7843277,838724790">2015.3.17</d>
<d p="26.784,1,25,16777215,1426598498,0,D0c4bb30,838726727">哔哩哔哩</d>
<d p="47.918,1,25,16777215,1426598519,0,D0c4bb30,838727141">哔哩哔哩</d>
<d p="68.651,1,25,16777215,1426601416,0,8ae211a0,838787836">哔哩哔哩哔哩哔哩</d>
<d p="18.588,1,25,16777215,1426602220,0,Ddac7e71,838804405">欢迎观看镇站之宝</d>
<d p="53.49,1,25,0,1426602368,0,3f4df401,838807491">舰炮滚</d>
<d p="86.174,5,25,65280,1426602384,0,3f4df401,838808140">见炮滚</d>
<d p="0.356,1,25,16777215,1426602532,0,e67c75af,838811010">其实这是危险的炮姐！！！</d>
<d p="92.317,1,25,16777215,1426602653,0,D9723979,838813561">最终之作最可爱</d>
<d p="68.92,5,25,41194,1426603929,0,54a75599,838839335">3.17来打我。？</d>
<d p="36.389,1,25,16711782,1426604021,0,ae656947,838841029">bilibili</d>
<d p="59.383,1,25,13369344,1426604041,0,5fed75fb,838841460">哔哩哔哩哔哩哔哩哔哩哔哩哔哩</d>
<d p="21.191,1,25,16777215,1426604156,0,d8450b83,838843725">BGM：机动戦士ガンダム-ココロオドル</d>
<d p="58.16,1,25,16777215,1426607305,0,05b9ff25,838897009">3.15</d>
<d p="31.341,1,25,16777215,1426608706,0,9c949aea,838914892">弹幕呢</d>
<d p="21.784,1,25,16777215,1426612256,0,c85d8a70,838945801">哔哩哔哩哔哩哔哩哔哩哔哩哔哩</d>
<d p="84.262,1,25,16777215,1426612894,0,c85d8a70,838949657">加油顶上去</d>
<d p="42.539,1,25,16777215,1426613306,0,9c5397e1,838952025">炮炮</d>
<d p="16.558,1,25,16777215,1426641871,0,c39c4655,839045504">一天一发</d>
<d p="53.506,1,25,15138834,1426645002,0,66d4bd61,839071225">3.9那个你别走～3.18来了</d>
<d p="25.731,1,25,6684774,1426645421,0,3cc5d302,839073709">镇站之宝留</d>
<d p="23.477,1,25,16777215,1426652973,0,019b5709,839138907">敢顶敢看</d>
<d p="30.166,1,25,16777215,1426653568,0,Dbc885e4,839146583">哔哩哔哩</d>
<d p="84.01,1,25,204,1426653754,0,71688890,839148732">2015/3/18</d>
<d p="93.666,1,25,16777215,1426653958,0,Ddafb020,839151689">哔哩哔哩哔哩哔哩</d>
<d p="33.972,1,25,16777215,1426654759,0,079b63fd,839162799">哔哩哔哩哔哩哔哩</d>
<d p="70.08,1,25,16777215,1426655240,0,775984b8,839169402">刷一发</d>
<d p="56.297,1,25,16777215,1426657915,0,a82dd01c,839209362">老坟</d>
<d p="37.692,1,25,16777215,1426657983,0,6cade7e8,839210054">怎么又顶上来了</d>
<d p="39.671,1,25,65433,1426666583,0,9a462136,839316978">哔哩哔哩哔哩哔哩哔哩哔哩</d>
<d p="11.406,1,25,16777215,1426669612,0,5c55202d,839357297">2015.3.18</d>
<d p="84.48,1,25,16777215,1426673094,0,50a99743,839397717">我看到小黄书了</d>
<d p="7.929,1,25,16777215,1426673220,0,81b42747,839399313">201</d>
<d p="20.702,1,25,16711680,1426673827,0,b63d428b,839407141">哔哩哔哩</d>
<d p="50.36,1,25,16777215,1426675487,0,D55e8a1f,839433136">不行发一个</d>
<d p="41.715,1,25,16777215,1426675885,0,3d62e683,839436691">哔哩哔哩弹幕</d>
<d p="66.88,1,25,16777215,1426675955,0,21a26ef7,839437959">3.18</d>
<d p="4.425,1,25,16777215,1426677704,0,Dbc15add,839486718">bilibilibilibilibili</d>
<d p="4.862,1,25,16777215,1426679964,0,30fc5715,839523728">哔哩哔哩</d>
<d p="27.345,1,25,16777215,1426680010,0,30fc5715,839524486">哔哩哔哩</d>
<d p="55.68,1,25,16777215,1426680470,0,D44c7253,839532277">2015.3.18←渣渣</d>
<d p="93.155,1,25,41194,1426680974,0,8e624994,839543391">前面2015.3.18的别走</d>
<d p="31.619,1,25,16777215,1426683114,0,Db2ba981,839581858">之前不是被删除了么  怎么又回来了</d>
<d p="26.387,1,25,16777215,1426684151,0,8bc62bd4,839602366">居然还有小伙伴存在</d>
<d p="54.36,4,25,16777215,1426684954,0,3a273f83,839618010">←_←一方出现</d>
<d p="10.406,1,25,16777215,1426685756,0,ed9142e8,839635609">独享成功</d>
<d p="76.659,1,25,16777215,1426685942,0,ed9142e8,839640012">炮姐好萌</d>
<d p="71.408,1,25,16777215,1426685960,0,D51efd95,839640423">御坂妹</d>
<d p="73.446,1,25,16777215,1426686035,0,D51efd95,839642267">炮姐</d>
<d p="36.76,1,25,16777215,1426686109,0,47d7c8f9,839644033">自带弹幕</d>
<d p="57.367,5,25,16776960,1426688482,0,77292c6c,839696300">2015.3.18来一发</d>
<d p="45.077,1,25,16777215,1426688688,0,83132522,839700798">哔哩哔哩</d>
<d p="74.816,1,25,16711680,1426688718,0,83132522,839701492">哔哩哔哩哔哩哔哩</d>
<d p="88.293,1,25,16711680,1426688699,0,83132522,839701793">3月18 </d>
<d p="42.132,1,25,3407871,1426691557,0,7aca15be,839759381">历史弹幕根本无法读取啊……- -</d>
<d p="5.893,1,25,16777215,1426692604,0,25a00f52,839780124">2015.3.18留念</d>
<d p="37.84,1,25,16777215,1426695500,0,470c571c,839817846">2015.3.19</d>
<d p="53.84,5,25,16707842,1426695586,0,dccba81c,839818698">我2015-3-18</d>
<d p="93.8,5,25,16707842,1426695648,0,dccba81c,839819301">3-3-18的等等我</d>
<d p="11.72,1,25,16777215,1426696816,0,1b6ab80b,839830201">美琴～</d>
<d p="17.874,1,25,16777215,1426696717,0,1b6ab80b,839830395">美琴好萌   </d>
<d p="46.44,1,25,16777215,1426707861,0,292b57dd,839889627">这个是天麻的那个杠杠杠杠么</d>
<d p="22.135,1,25,16777215,1426742421,0,ca9b3862,840072660">自带循环。。。。。。</d>
<d p="25.159,1,25,16777215,1426742543,0,Da0aefd3,840074968">哔哩哔哩~~~</d>
<d p="0.362,1,25,16777215,1426745129,0,1650db13,840103587">循环4个小时了。。停不下来啊</d>
<d p="31.448,1,25,16777215,1426745432,0,Da5ade7f,840106219">炮姐~~</d>
<d p="14.232,1,25,16777215,1426745470,0,f397d110,840106584">这尼玛又上</d>
<d p="22.856,1,25,16777215,1426748215,0,D8c6194b,840129707">我又回来了</d>
<d p="19.088,1,25,16777215,1426754603,0,25236da9,840184987">哔哩哔哩？？？ </d>
<d p="24.459,1,25,16777215,1426754612,0,25236da9,840185072">哔哩哔哩？</d>
<d p="24.459,1,25,16777215,1426754661,0,25236da9,840185149">哔哩哔哩哔哩哔哩</d>
<d p="45.143,1,25,16777215,1426757255,0,64236e07,840220590">顶他娘的啊！！！！！！！！</d>
<d p="30.224,1,25,16777215,1426757365,0,64236e07,840221784">哔哩哔哩真是太好了！</d>
<d p="20.638,1,25,16777215,1426757399,0,64236e07,840222608">哔哩哔哩什么的最爱了！！！！</d>
<d p="42.784,1,25,16777215,1426757445,0,64236e07,840222855">500的弹幕池不够啊</d>
<d p="10.822,1,25,16777215,1426757527,0,64236e07,840223549">自带循环啊、、、、、、、</d>
<d p="18.623,1,25,13369344,1426757776,0,64236e07,840226418">无限循环啊</d>
<d p="78.595,1,25,16777215,1426759551,0,dd8a54ec,840255421">哔哩哔哩</d>
<d p="17.543,1,25,16777215,1426763678,0,930c650a,840318727">41</d>
<d p="24.015,1,25,16777215,1426765126,0,Df79601b,840343601">找了好久~~~~~~~~~~~~~</d>
<d p="53.3606,5,25,14811775,1426767094,0,6fe99ae6,840380034">2015.3.19看你</d>
<d p="39.725,1,25,16777215,1426767180,0,72f23cde,840381621">哔哩哔哩哔哩哔哩</d>
<d p="87.318,1,25,16777215,1426773089,0,ae7974e5,840498015">bilibili</d>
<d p="10.435,1,25,16711680,1426774282,0,ac1eb2f6,840522186">为啥回来了</d>
<d p="19.101,1,25,16711680,1426774292,0,ac1eb2f6,840522383">为啥回来了</d>
<d p="15.04,5,25,15772458,1426775651,0,e87fd44d,840549553">3.19还有谁。。bilibili。。</d>
<d p="48.52,1,25,15772458,1426775711,0,e87fd44d,840550755">哔哩哔哩哔哩哔哩比例</d>
<d p="18.237,1,25,43758,1426811784,0,f9551d6f,840779650">臥槽贊(≧▽≦)</d>
<d p="1.64,1,25,16777215,1426812632,0,51ba07f9,840782573">据说是真站至宝</d>
<d p="20.532,1,25,16777215,1426812696,0,3180ec85,840782814">卧槽有顶上来了</d>
<d p="12.638,1,25,16777215,1426812713,0,4730116e,840782879">简直刷屏</d>
<d p="53.086,1,25,16777215,1426812754,0,4730116e,840783031">比利比利♂~~~~~~</d>
<d p="96.13,1,25,16777215,1426828270,0,5bc2d27b,840916998">320留</d>
<d p="3.88,1,25,16777215,1426831962,0,Da520ea6,840965382">2015·3·20</d>
<d p="8.331,1,25,16777215,1426832796,0,932a9c30,840973284">听说这个弹幕很屌</d>
<d p="69.115,1,25,16777215,1426834155,0,38a5fb2a,840985607">2333333333</d>
<d p="0,1,25,16777215,1426836829,0,0d688b95,841010174">无限小电视</d>
<d p="77.575,1,25,16777215,1426839644,0,D54dcdba,841034769">3.20</d>
<d p="15.091,1,25,16777215,1426839904,0,09c8a312,841037411">什么鬼</d>
<d p="43.833,1,25,16777215,1426840308,0,4350626e,841041620">哔哩哔哩哔哩哔哩</d>
<d p="5.68,1,25,16777215,1426840411,0,80dc2fc1,841042725">自带循环 </d>
<d p="94.305,1,25,16777215,1426840575,0,d1d59ed3,841044434">2015.3.20</d>
<d p="44.732,5,25,65535,1426841166,0,1807570e,841050795">一天不看不舒服</d>
<d p="3.635,1,25,16777215,1426841181,0,7f8f3782,841050938">2015.3.20</d>
<d p="13.011,1,25,16777215,1426845174,0,527b79b5,841104921">bilibili</d>
<d p="28.458,1,25,16777215,1426849686,0,46a39bac,841186010">独享成功</d>
<d p="65.39,1,25,16777215,1426849884,0,baa852db,841190080">醉了醉了醉了醉了</d>
<d p="48.8,1,25,9599289,1426853426,0,3a273f83,841268615">什么是高级弹幕要电脑么</d>
<d p="17.705,1,25,16777215,1426855206,0,4455f2f1,841312211">没人顶了吗？</d>
<d p="51.321,1,25,16777215,1426860489,0,be80c5e7,841445791">bilibilibilibilibilibili</d>
<d p="22.988,1,25,16777215,1426860542,0,01e64f07,841447022">bilibili</d>
<d p="79.588,1,25,16777215,1426867176,0,f958d707,841600786">-.-</d>
<d p="23.936,1,25,16777215,1426875939,0,D91ce362,841708459">突破两百万了</d>
<d p="26.471,1,25,16777215,1426876247,0,532712ff,841710620">从来不穿 胖次 的哔哩哔哩初中生</d>
<d p="44.999,1,25,13382502,1426888693,0,e02a09ab,841754595">公主      </d>
<d p="39.569,1,25,16777215,1426905154,0,b75c814a,841851797">哔哩哔哩哔哩哔哩</d>
<d p="62.15,1,25,16777215,1426914523,0,8f22886a,842008503">炮姐 炮姐 炮姐</d>
<d p="7.88,5,25,16707842,1426914544,0,9040767b,842008964">每日来一次</d>
<d p="54.718,5,25,3342540,1426914612,0,8f22886a,842010265">炮姐 炮姐</d>
<d p="10.675,1,25,16777215,1426918426,0,50e9afc7,842082606">bilibilibili</d>
<d p="67.76,1,25,16777215,1426918599,0,Dd12d113,842085622">哔喱 哔喱 哔喱 哔喱 哔喱 哔喱</d>
<d p="11.228,5,25,3407616,1426918718,0,4850d932,842087726">！！！</d>
<d p="23.68,5,25,3407616,1426918729,0,4850d932,842087963">我炮美如画</d>
<d p="62.981,5,25,3407616,1426918769,0,4850d932,842088664">考古</d>
<d p="92.773,4,25,3381708,1426918834,0,d8ceccf7,842089824">我就知道出不去的~~~~~~</d>
<d p="15.377,4,18,16777215,1426918925,0,af07e46f,842091415">卧槽</d>
<d p="40.547,4,18,10092543,1426919051,0,af07e46f,842093764">收藏的都是什么心态</d>
<d p="56.9,5,18,10092543,1426919080,0,af07e46f,842094283">3.21！！！！</d>
<d p="22.765,1,25,16777215,1426923040,0,e8a0ab41,842203709">哔哩哔哩</d>
<d p="0,1,25,16777215,1426924304,0,bc9e5b2e,842227061">庆祝重生！让我们再次开始搞比例吧！</d>
<d p="62.68,1,25,16777215,1426925410,0,Dca89606,842247669">2015.3.21成功挖出镇站之宝</d>
<d p="49.038,1,25,15772458,1426931516,0,18bd9c05,842370111">3.21美琴赛高</d>
<d p="43.02,1,25,16777215,1426934034,0,8886b663,842427153">哔哩哔哩</d>
<d p="10.702,1,25,16777215,1426936030,0,c3aed4e1,842476030">哔哩哔哩</d>
<d p="10.702,5,25,16777215,1426936046,0,c3aed4e1,842476428">哔哩哔哩</d>
<d p="19.008,1,25,16777215,1426936307,0,e8b479f4,842482950">！！！！</d>
<d p="27.45,1,18,16777215,1426936316,0,e8b479f4,842483135">！！！！！</d>
<d p="9.745,1,25,16777215,1426936418,0,32056b6f,842485582">我去 好可怕的样子</d>
<d p="12.192,1,25,16777215,1426936436,0,9f9830e8,842485971">哔哩哔哩哔哩哔哩哔哩哔哩哔哩</d>
<d p="24.09,1,18,16711680,1426936443,0,32056b6f,842486165">真的好可怕..</d>
<d p="19.351,1,25,16777215,1426937605,0,db650bb8,842515312">2015.3.21</d>
<d p="52.92,5,25,16707842,1426942397,0,02c4d80a,842651582">2015.3.20</d>
<d p="19.934,1,25,16777215,1426943114,0,D3eb9722,842672219">。。</d>
<d p="36.205,1,25,16777215,1426943132,0,D3eb9722,842672662">等我</d>
<d p="28.919,1,25,16777215,1426943190,0,D94cb6ad,842674466">这是逼老夫来诈尸</d>
<d p="22.08,1,25,16777215,1426943249,0,d54043c0,842676350">谁又顶上来了</d>
<d p="59.659,1,25,16776960,1426943253,0,7a89a60f,842676472">                                                 哔哩哔哩哔哩哔哩哔哩哔哩哔哩</d>
<d p="2.6,1,25,16777215,1426944050,0,b65ee225,842701709">听说被删了回来看看</d>
<d p="4.235,1,25,8700107,1426946448,0,d2a156c6,842774388">2015.3.21 答完题后慕名前来看镇站之宝</d>
<d p="12.05,1,25,16777215,1426947883,0,de03d79e,842815245">弹幕支援</d>
<d p="67.774,1,25,16777215,1426947938,0,de03d79e,842816899">永远有人陪看~~</d>
<d p="30.728,1,25,16777215,1426948073,0,cbcc1301,842820659">哔哩哔哩哔哩哔哩哔哩哔哩</d>
<d p="18.177,1,25,16777215,1426948608,0,bc2a34e5,842838403">独享成功</d>
<d p="37.24,1,25,16777215,1426948686,0,Dd65aa7a,842840576">洛阳铲~\(≧▽≦)/~</d>
<d p="46.56,1,25,16777215,1426948705,0,Dd65aa7a,842841016">炮姐么么哒~\(≧▽≦)/~</d>
<d p="18.682,1,25,16777215,1426948738,0,4b27ec15,842842053">misako mikoto!!!!!!!</d>
<d p="70.48,1,25,16777215,1426948741,0,Dd65aa7a,842842074">2015.3.21~\(≧▽≦)/~</d>
<d p="79.2,1,25,16777215,1426948755,0,Dd65aa7a,842842462">duang</d>
<d p="33.96,1,25,16777215,1426950008,0,d8926496,842878070">见到炮姐来一发。</d>
<d p="43.92,1,25,16777215,1426950038,0,d8926496,842878741">哔哩哔哩哔哩哔哩</d>
<d p="15.562,1,25,16777215,1426950644,0,7cc84bfa,842894903">神弹幕合影</d>
<d p="26.056,1,25,16777215,1426950676,0,1b6ab80b,842895726">没有长弹幕了。。</d>
<d p="51.264,1,25,16777215,1426950713,0,1b6ab80b,842896740">Misaka misaka</d>
<d p="9.184,1,25,16777215,1426950999,0,a2e870a2,842903653">来测试下电脑性能！！</d>
<d p="78.166,1,25,16777215,1426951068,0,a2e870a2,842905242">哔哩哔哩哔哩哔哩</d>
<d p="39.605,1,25,16777215,1426956580,0,ab4311c0,843011525">每当心情不好时就进来接受哔哩哔哩的洗礼</d>
<d p="47.592,1,25,16777215,1426959334,0,86fee17b,843044606">哔哩哔哩</d>
<d p="47.592,1,25,16777215,1426959343,0,86fee17b,843044693">bilibili</d>
<d p="82.84,1,25,16777215,1426985287,0,3e57e568,843185529">3.21</d>
<d p="38.895,1,25,16777215,1426988796,0,fe56c2ab,843219191">哔哩哔哩哔哩哔哩</d>
<d p="24.746,1,25,16777215,1426989083,0,Dfb31d28,843222904">哔哩哔哩</d>
<d p="34.073,1,25,16777215,1426989269,0,5e1b69ff,843225146">(ノ=Д=)ノ┻━┻ 电脑显卡CPU全开！</d>
<d p="24.102,1,25,16777215,1426991325,0,64f1431d,843254683">哔哩哔哔哩哔哩</d>
<d p="53.025,1,25,16777215,1426991451,0,283e5162,843256723">哔哩哔哩</d>
<d p="39.991,4,18,13369395,1426991518,0,a489fdd3,843257780">卧槽 这弹幕</d>
<d p="53.435,1,25,16777215,1426992451,0,0ef885b9,843272923">哔哩哔哩哔哩哔哩哔哩哔哩</d>
<d p="62.731,1,25,16777215,1426992460,0,0ef885b9,843273090">哔哩哔哩哔哩哔哩哔哩哔哩</d>
<d p="81.618,1,25,16724889,1426992547,0,0d68db9a,843274599">什么鬼</d>
<d p="65.286,1,25,13369344,1426993174,0,248b2563,843285794">我叫杨震我最帅</d>
<d p="77.478,1,25,13369344,1426993186,0,248b2563,843286017">我叫杨震我最帅</d>
<d p="91.526,1,25,13369344,1426993200,0,248b2563,843286299">我叫杨震我最帅</d>
<d p="2.384,1,25,16777215,1426995647,0,e9f7c258,843332450">びりびり</d>
<d p="38.539,1,25,3394713,1427000224,0,37debf05,843426813">哔哩哔哩哔哩哔哩</d>
<d p="60.173,1,25,6710988,1427000802,0,2312e076,843440109">哔哩哔哩</d>
<d p="84.342,1,25,16777215,1427001151,0,cf5e96b3,843447952">哔喱哔喱</d>
<d p="7.626,1,25,16711680,1427001364,0,2e0be0da,843452622">哔哩哔哩哔哩哔哩</d>
<d p="92.862,1,25,16777215,1427004140,0,9c61ad9f,843519749">简直了</d>
<d p="20.369,1,25,16777215,1427004729,0,98f65f81,843532587">镇站之宝</d>
<d p="29.004,1,25,16777215,1427004738,0,98f65f81,843532751">炮姐再战五百年</d>
<d p="56.304,1,25,16777215,1427004765,0,98f65f81,843533437">唯我超电磁炮永世长存</d>
<d p="43.019,1,25,16777215,1427004845,0,98f65f81,843535297">处女币献上了</d>
<d p="88.1,1,25,16777215,1427004989,0,98f65f81,843538345">陷入循环坑出不来了</d>
<d p="24.274,1,25,16777215,1427005022,0,98f65f81,843539017">2015.3.22</d>
<d p="58.003,1,25,16777215,1427008408,0,da5dabd0,843614142">顶</d>
<d p="1.761,1,25,16777215,1427008665,0,c4365db0,843620103">15500个弹幕</d>
<d p="61.784,1,25,153,1427012379,0,d8064e19,843700527">←3.18的等我</d>
<d p="72.614,1,18,16777215,1427012459,0,e3c27534,843703040">   我是来试弹幕的          </d>
<d p="26.276,1,25,16777215,1427012585,0,568e4196,843706045">弹幕太凶残</d>
<d p="5.842,1,25,16777215,1427014467,0,9c61ad9f,843746192">果然bilibili</d>
<d p="92.8,1,25,16777215,1427014473,0,Daf806d9,843746386">2015.3.22</d>
<d p="0,1,25,16777215,1427014714,0,7357b2cc,843751457">见炮滚</d>
<d p="45.093,1,25,16777215,1427015221,0,D93b1b85,843762357">2015.3.22</d>
<d p="44.789,1,25,16777215,1427024184,0,e27e64d6,843962396">哔哩哔哩</d>
<d p="20.601,1,25,16777215,1427027509,0,1b6ab80b,844053088">来一发～美琴我爱你</d>
<d p="34.285,1,25,16777215,1427029129,0,f0955588,844094141">2015 3 22一个人</d>
<d p="3.563,1,25,16777215,1427029784,0,6225dcd9,844110908">哔哩哔哩</d>
<d p="63.021,1,25,16777215,1427029849,0,6225dcd9,844112522">哔哩哔哩</d>
<d p="55.446,1,25,16777215,1427037004,0,939f0f3a,844279514">悠哉日常大王</d>
<d p="74.036,1,25,16777215,1427042792,0,2fae53c8,844359783">独享成功</d>
<d p="40.903,1,25,16711680,1427045888,0,5eb6b4ea,844382125">shoucang baobiao</d>
<d p="38.614,1,25,16777215,1427077379,0,9e4652d6,844485718">安全裤</d>
<d p="52.935,1,25,16777215,1427086954,0,e48d8100,844651710">=-=</d>
<d p="85.817,1,25,16777215,1427088260,0,Da48a612,844669684">哔哩哔哩</d>
<d p="56.678,1,25,16777215,1427088476,0,b62c6160,844672338">2015.3.23</d>
<d p="34.02,1,25,16777215,1427102726,0,fc26ac12,844836239">镇站之宝？</d>
<d p="13.217,5,25,14811775,1427108165,0,29b84b2c,844914516">2015.3.23谁比我早！</d>
<d p="58.742,4,25,16777215,1427108371,0,d22f1765,844917913">3.23</d>
<d p="46.857,4,25,15138834,1427109772,0,3abacd77,844944960">哔哩哔哩zqq</d>
<d p="58.29,4,25,15138834,1427109790,0,3abacd77,844945255">哔哩哔哩</d>
<d p="89.333,4,25,15138834,1427109931,0,3abacd77,844947665">ajajajajaj</d>
<d p="5.367,1,25,16777215,1427113579,0,29be1cfe,845013905">好恐怖</d>
<d p="33.002,1,25,16777215,1427113608,0,29be1cfe,845014439">镇站之宝</d>
<d p="25.984,1,25,16777215,1427113693,0,29be1cfe,845016110">哔哩哔哩比利哔哩哔哩</d>
<d p="61.4718,1,25,16777215,1427115785,0,Df94d50c,845058387">3.23</d>
<d p="20.807,1,25,16777215,1427118114,0,98f65f81,845109230">我大炮姐还能再战五百年</d>
<d p="49.055,1,25,16724736,1427118147,0,98f65f81,845109761">炮姐赛高</d>
<d p="80.802,1,25,16724736,1427118176,0,98f65f81,845110406">哔哩哔哩哔哩哔哩</d>
<d p="1.016,1,25,16724736,1427118192,0,98f65f81,845110770">卡！哇！伊！</d>
<d p="21.333,1,25,16724736,1427118215,0,98f65f81,845111207">唯我超电磁炮永世长存</d>
<d p="52.185,1,25,16724736,1427118246,0,98f65f81,845111851">明知是无限循环坑却不想出去的一定不止我一个</d>
<d p="88.12,1,25,16724736,1427118282,0,98f65f81,845112583">卡哇伊</d>
<d p="10.711,1,25,16724736,1427118301,0,98f65f81,845112991">初心不改此琴不变</d>
<d p="59.209,1,25,16724736,1427118349,0,98f65f81,845114152">弹幕可以被清但我们的爱不会变√</d>
<d p="87.677,1,25,16724736,1427118378,0,98f65f81,845114799">炮姐一生推</d>
<d p="13.062,1,25,16724736,1427118399,0,98f65f81,845115300">弹幕由我们组成</d>
<d p="19.529,1,25,16724736,1427118404,0,98f65f81,845115421">misakamikoto</d>
<d p="29.152,1,25,16724736,1427118411,0,98f65f81,845115652">哔哩哔哩</d>
<d p="44.199,1,25,16724736,1427118430,0,98f65f81,845115982">姐姐大人美如画</d>
<d p="58.303,1,25,16724736,1427118444,0,98f65f81,845116276">黑子愿意成为姐姐大人的力量</d>
<d p="74.821,1,25,16724736,1427118482,0,98f65f81,845117199">妹妹腹黑萌</d>
<d p="0.01,1,25,16724736,1427118504,0,98f65f81,845117645">我家炮姐的脸是你们这些凡人可以看的吗</d>
<d p="41.316,1,25,16724736,1427118546,0,98f65f81,845118570">顶上去！镇站之宝永不沉1</d>
<d p="69.351,1,25,16724736,1427118574,0,98f65f81,845119204">早日破300w</d>
<d p="39.054,1,25,16724736,1427118638,0,98f65f81,845120793">真 镇站之宝</d>
<d p="84.259,1,25,16724736,1427118685,0,98f65f81,845121982">你的背后交给我们</d>
<d p="13.811,1,25,16724736,1427118711,0,98f65f81,845122552">你指尖闪烁的电光是我一生不变的信仰</d>
<d p="57.577,1,25,16724736,1427118755,0,98f65f81,845123564">每天睡前看一遍</d>
<d p="25.658,1,25,16724736,1427118817,0,98f65f81,845125054">来b站专门看炮姐</d>
<d p="22.735,1,25,16777215,1427118956,0,af881bac,845128058">弹幕被清啦</d>
<d p="81.152,1,25,16777215,1427121434,0,470c571c,845178359">2015.3.23</d>
<d p="90.426,1,25,16777215,1427122103,0,61b4fa95,845191676">200W的点击，太少了</d>
<d p="23.639,1,25,16777215,1427131163,0,4d9fa751,845313881">镇站之宝</d>
<d p="78.717,1,25,16777215,1427159981,0,afd7129f,845387732">哔哩哔哩哔哩哔哩哔哩哔哩</d>
<d p="60.042,1,25,16777215,1427170696,0,fe91333a,845446817">3.24</d>
<d p="69.665,1,25,16777215,1427170703,0,fe91333a,845446919">3.24</d>
<d p="75.827,1,25,16777215,1427170706,0,fe91333a,845446968">3.24</d>
<d p="49.841,1,25,16777215,1427170864,0,95c884d8,845448613">bilibibili</d>
<d p="2.44,1,25,16777215,1427171035,0,3abacd77,845450389">戴一铭强暴了郭洋洋</d>
<d p="11.64,4,25,9599289,1427171065,0,3abacd77,845450719">戴一铭强暴了郭洋洋</d>
<d p="30.56,4,25,16707842,1427171457,0,3abacd77,845454999">戴一铭干的</d>
<d p="12.44,4,25,38979,1427171566,0,3abacd77,845456088">戴一铭强暴了郭洋洋</d>
<d p="12.24,4,25,14811775,1427171678,0,3abacd77,845457355">戴一铭强暴了郭洋洋</d>
<d p="31.68,4,25,11890,1427171698,0,3abacd77,845457683">戴一铭干的</d>
<d p="73.6,1,25,15772458,1427171800,0,3abacd77,845458968">2015.3.24zqq</d>
<d p="12.2,4,25,41194,1427171846,0,3abacd77,845459557">戴一铭强暴了郭洋洋</d>
<d p="81.4,4,25,41194,1427171934,0,3abacd77,845460511">大家啊哦</d>
<d p="82.32,5,25,14811775,1427171953,0,3abacd77,845460753">大家好我是炮姐红</d>
<d p="83.2,1,25,14811775,1427172170,0,3abacd77,845463620">大家好我是炮姐粉</d>
<d p="4.76,5,25,16777215,1427172222,0,3abacd77,845464296">戴一铭是av314主角？</d>
<d p="28.44,1,25,8700107,1427172299,0,3abacd77,845465296">戴一铭怒刷存在感</d>
<d p="53.84,1,25,8700107,1427172321,0,3abacd77,845465694">刚才baiyi</d>
<d p="61.08,5,25,16707842,1427172341,0,3abacd77,845465970">哔哩哔哩哔哩哔哩</d>
<d p="12.44,4,25,6830715,1427172483,0,3abacd77,845467628">戴一铭强暴了郭洋洋</d>
<d p="41.84,1,25,15138834,1427172535,0,3abacd77,845468404">谁她妈能告诉我戴一铭是谁？</d>
<d p="23.594,1,25,16777215,1427172799,0,860c3a20,845471958">哔哩哔哩哔哩哔哩哔哩哔哩</d>
<d p="12.261,1,25,16777215,1427172877,0,623e2cda,845473069">1000w 走起！</d>
<d p="71.813,5,25,16724889,1427189143,0,40d9b7d1,845634851">2015/3/24</d>
<d p="18.46,1,25,16777215,1427192193,0,e48171ed,845671320">无限循环？！！！</d>
<d p="27.371,1,25,16777215,1427192247,0,5d2edc4a,845672276">炮姐嫁我</d>
<d p="33.637,1,25,65280,1427193436,0,1c85a8ec,845691332">哔哩哔哩 哔哩哔哩哔哩哔哩</d>
<d p="38.888,1,25,16777215,1427195724,0,b63d428b,845728684">哔哩哔哩</d>
<d p="1.08,5,25,15772458,1427204320,0,3abacd77,845902615">我的弹幕呢zqq</d>
<d p="37.307,1,25,16777215,1427207638,0,D8bfe02a,845971585">bilibilibilibilibili</d>
<d p="17.647,1,25,15597687,1427208563,0,f6da39ea,845989961">哈哈哈，炮姐噻高▽</d>
<d p="85.184,1,25,16777215,1427208603,0,0049011f,845990778">弹幕来一发</d>
<d p="6.653,5,25,16777215,1427209412,0,d808e620,846007096">镇站之宝哔哩哔哩～</d>
<d p="45.471,1,25,16777215,1427209508,0,f1ac9b28,846008756">卧槽这恐怖的弹幕</d>
<d p="82.0777,1,25,16777215,1427211298,0,Db2213c0,846053917">哔哩哔哩哔哩哔哩</d>
<d p="0.4,7,45,16711680,1291576653,1,d2b8a56b,837813570">["101","130","1.00-1.00","4.50","と"]</d>
<d p="0,5,36,16724838,1296570581,1,32b191ae,837819922">BILIBILIBILIBILIBILIBILIBILIBILIBILIBILIBILIBILIBILIBILIBILIBILIBILIBILIBILIBILIBILIBILIBILIBILIBILIBILIBILIBILIBILIBILIBILIBILIBILIBILIBILIBILIBILIBILIBILIBILIBILIBILIBILIBILIBILIBILIBILIBILIBILIBILIBILIBILIBILIBILIBILI</d>
<d p="3.1,1,25,16777215,1296747564,1,7423e93b,837820269">Bilibi bilibibilibilibiliblibibilibilibilibilibilibilibilibilibilibilibilibi</d>
<d p="3.2,7,25,16777215,1310171155,1,9bd49c01,837839826">/n/n/n/n ~~BILIBILI</d>
<d p="3.2,7,25,10053222,1310171183,1,9bd49c01,837839828">- -</d>
<d p="3.2,1,25,10053222,1310171212,1,9bd49c01,837839830">.</d>
<d p="95.67,8,25,16777215,1365924729,2,4ea8db78,837982082">Player.seek(0);</d>
<d p="1,8,25,16777215,1408769749,2,e64def10,837982083">/* From 「Magical Mirai 2013」 */
/* 哔哩哔哩哔哩哔哩 */
var i = 0;
function printdanmuku(){
interval(function() {
	i++;
	var w = Player.width;
	var h = Player.height;
	var cy = Utils.rand(0, h);
	var c = $.createComment("哔哩哔哩哔哩哔哩哔哩哔哩哔哩哔哩哔哩哔哩哔哩哔哩", {
		y: cy,
		lifeTime: 2,
		motionGroup: [{
			alpha: {
				fromValue: 0.8,
				toValue: 0.8,
				lifeTime: 0
			}
		},
		{
			alpha: {
				fromValue: 0.8,
				toValue: 0.8,
				lifeTime: 0
			}
		}],
		fontsize: Utils.rand(w / 50, w / 15)
	});
	var col = Utils.rand(0x222222, 0xCCCCCC);
	c.color = col; (Tween.tween(c, {
		x: 0 - c.textWidth
	},
	{
		x: w
	},
	1, none)).play();
},
100, 550);
}
printdanmuku();
printdanmuku();</d>
</i>
